proxifyapps/NLog.config
proxifyapps/NLog.dll
proxifyapps/NLog.xml
proxifyapps/Newtonsoft.Json.dll
proxifyapps/Newtonsoft.Json.xml
proxifyapps/ProxiFyre.exe
proxifyapps/ProxiFyre.exe.config
proxifyapps/README.MD
proxifyapps/Topshelf.dll
proxifyapps/Topshelf.xml
proxifyapps/__init__.py
proxifyapps/requirements.txt
proxifyapps/socksify.dll
proxifyapps/thirdparty.json
proxifyapps-0.10.dist-info/LICENSE.rst
proxifyapps-0.10.dist-info/METADATA
proxifyapps-0.10.dist-info/WHEEL
proxifyapps-0.10.dist-info/top_level.txt
proxifyapps-0.10.dist-info/RECORD
