Metadata-Version: 2.1
Name: proxifyapps
Version: 0.10
Summary: wrapper for proxifyre
Home-page: https://github.com/hansalemaos/proxifyapps
Author: Johannes Fischer
Author-email: aulasparticularesdealemaosp@gmail.com
License: MIT
Keywords: proxy
Classifier: Development Status :: 4 - Beta
Classifier: Programming Language :: Python :: 3 :: Only
Classifier: Programming Language :: Python :: 3.10
Classifier: Topic :: Software Development :: Libraries :: Python Modules
Classifier: Topic :: Utilities
License-File: LICENSE.rst
Requires-Dist: ctrlchandler
Requires-Dist: deepcopyall
Requires-Dist: flatten-any-dict-iterable-or-whatsoever
Requires-Dist: mainprocess
Requires-Dist: multikeyiterdict
Requires-Dist: suicideproc
Requires-Dist: touchtouch
Requires-Dist: umacajadada
